pyruleanalyzer/__init__.py
pyruleanalyzer/rule_classifier.py
pyruleanalyzer-1.1.1.dist-info/licenses/LICENSE
pyruleanalyzer-1.1.1.dist-info/METADATA
pyruleanalyzer-1.1.1.dist-info/WHEEL
pyruleanalyzer-1.1.1.dist-info/top_level.txt
pyruleanalyzer-1.1.1.dist-info/RECORD
