Metadata-Version: 2.4
Name: pyruleanalyzer
Version: 1.1.1
Author: GrupoCybersegurancaVirtus
License-Expression: MIT
Project-URL: Homepage, https://github.com/GrupoCybersegurancaVirtus/pyruleanalyzer
Project-URL: Documentation, https://grupocybersegurancavirtus.github.io/pyruleanalyzer/
Classifier: Programming Language :: Python :: 3
Classifier: Operating System :: OS Independent
Requires-Python: >=3.7
License-File: LICENSE
Requires-Dist: numpy
Requires-Dist: pandas
Requires-Dist: scikit-learn
Requires-Dist: matplotlib
Provides-Extra: docs
Requires-Dist: sphinx; extra == "docs"
Requires-Dist: sphinx-autobuild; extra == "docs"
Requires-Dist: sphinx_rtd_theme; extra == "docs"
Requires-Dist: sphinxcontrib-bibtex; extra == "docs"
Dynamic: license-file
